README.txt
setup.py
collective/__init__.py
collective.namedfile.egg-info/PKG-INFO
collective.namedfile.egg-info/SOURCES.txt
collective.namedfile.egg-info/dependency_links.txt
collective.namedfile.egg-info/namespace_packages.txt
collective.namedfile.egg-info/not-zip-safe
collective.namedfile.egg-info/requires.txt
collective.namedfile.egg-info/top_level.txt
collective/namedfile/__init__.py
collective/namedfile/browser.py
collective/namedfile/configure.zcml
collective/namedfile/displaywidget.pt
collective/namedfile/field.py
collective/namedfile/file.py
collective/namedfile/image.py
collective/namedfile/imagedisplaywidget.pt
collective/namedfile/imageinputwidget.pt
collective/namedfile/inputwidget.pt
collective/namedfile/interfaces.py
collective/namedfile/widget.py
docs/CHANGES.txt
docs/LICENSE.txt
docs/TODO.txt