Metadata-Version: 1.0
Name: collective.namedfile
Version: 1.2
Summary: File field and widget with enhancements for zope3.
Home-page: http://svn.plone.org/svn/collective/collective.namedfile
Author: Laurence Rowe
Author-email: l@lrowe.co.uk
License: ZPL 2.1
Platform: UNKNOWN
Classifier: Framework :: Zope3
Classifier: Programming Language :: Python
Classifier: License :: OSI Approved :: Zope Public License
Classifier: Operating System :: OS Independent
Classifier: Topic :: Internet :: WWW/HTTP :: Dynamic Content
Classifier: Topic :: Software Development :: Libraries :: Python Modules
